odoo/addons/crm_klaviyo/README.rst
odoo/addons/crm_klaviyo/__init__.py
odoo/addons/crm_klaviyo/__manifest__.py
odoo/addons/crm_klaviyo/i18n/crm_klaviyo.pot
odoo/addons/crm_klaviyo/i18n/it.po
odoo/addons/crm_klaviyo/models/__init__.py
odoo/addons/crm_klaviyo/models/klaviyo_account.py
odoo/addons/crm_klaviyo/readme/CONFIGURE.rst
odoo/addons/crm_klaviyo/readme/CONTRIBUTORS.rst
odoo/addons/crm_klaviyo/readme/DESCRIPTION.rst
odoo/addons/crm_klaviyo/readme/USAGE.rst
odoo/addons/crm_klaviyo/security/ir.model.access.csv
odoo/addons/crm_klaviyo/static/description/icon.png
odoo/addons/crm_klaviyo/static/description/icon.svg
odoo/addons/crm_klaviyo/static/description/index.html
odoo/addons/crm_klaviyo/tests/__init__.py
odoo/addons/crm_klaviyo/tests/test_crm_klaviyo.py
odoo/addons/crm_klaviyo/views/klaviyo_account.xml
odoo12_addon_crm_klaviyo-12.0.1.0.0.99.dev6.dist-info/METADATA
odoo12_addon_crm_klaviyo-12.0.1.0.0.99.dev6.dist-info/WHEEL
odoo12_addon_crm_klaviyo-12.0.1.0.0.99.dev6.dist-info/top_level.txt
odoo12_addon_crm_klaviyo-12.0.1.0.0.99.dev6.dist-info/RECORD
