Metadata-Version: 2.1
Name: odoo12-addon-crm-klaviyo
Version: 12.0.1.0.0.99.dev6
Summary: Manage Klaviyo API keys
Home-page: https://github.com/OCA/crm
Author: Hunki Enterprises BV, Odoo Community Association (OCA)
Author-email: support@odoo-community.org
License: AGPL-3
Platform: UNKNOWN
Classifier: Programming Language :: Python
Classifier: Framework :: Odoo
Classifier: Framework :: Odoo :: 12.0
Classifier: License :: OSI Approved :: GNU Affero General Public License v3
Classifier: Development Status :: 3 - Alpha
Requires-Python: >=3.5
Requires-Dist: dataclasses
Requires-Dist: klaviyo-api
Requires-Dist: odoo <12.1dev,>=12.0a
